[
  {
    "title": "Smorgasbord",
    "description": "This list is the modular buffet table of the very best mods available for 7 Days to Die.",
    "author": "FNS",
    "maintainers": [
      "github/Fluffernuttersandwich"
    ],
    "game": "sevendaystodie",
    "official": false,
    "tags": [
      "QoL",
      "Vanilla\u002B"
    ],
    "nsfw": false,
    "utility_list": false,
    "image_contains_title": true,
    "DisplayVersionOnlyInInstallerView": false,
    "force_down": false,
    "links": {
      "image": "https://raw.githubusercontent.com/Fluffernuttersandwich/Smorgasbord/main/Smorg5.webp",
      "readme": "https://raw.githubusercontent.com/Fluffernuttersandwich/Smorgasbord/main/README.md",
      "download": "https://authored-files.wabbajack.org/Smorgasbord.wabbajack_94f4f262-31c6-4bb5-95fb-1f11ac82219f",
      "machineURL": "Smorgasbord",
      "discordURL": "https://discord.gg/WpVPJWj7Xk",
      "websiteURL": "https://github.com/Fluffernuttersandwich/Smorgasbord",
      "nexusCollection": null
    },
    "download_metadata": {
      "Hash": "rrSZxuvylEc=",
      "Size": 6659833,
      "NumberOfArchives": 536,
      "SizeOfArchives": 39336599115,
      "NumberOfInstalledFiles": 74292,
      "SizeOfInstalledFiles": 59187046197,
      "TotalSize": 98523645312
    },
    "version": "2.6.1.8",
    "dateCreated": "1970-01-01T00:00:00Z",
    "dateUpdated": "2026-04-19T23:22:09.8026944Z",
    "repositoryName": "Better 7DTD"
  }
]